QM.py
__init__.py
example.py
test_library.py
QM_KU-1.1.data/scripts/QM.py
QM_KU-1.1.data/scripts/__init__.py
QM_KU-1.1.dist-info/LICENSE
QM_KU-1.1.dist-info/METADATA
QM_KU-1.1.dist-info/WHEEL
QM_KU-1.1.dist-info/top_level.txt
QM_KU-1.1.dist-info/RECORD
