Metadata-Version: 2.1
Name: QM-KU
Version: 1.1
Summary: QM library introducing vector-like and matrix like bra, ket, and operator classes
Home-page: UNKNOWN
Author: Rasmus Skytte Eriksen
Author-email: rasmus.eriksen@nbi.ku.dk
License: cc-by-sa-4.0
Platform: UNKNOWN
Requires-Dist: numpy
